.gitignore
.travis.yml
CHANGES
MANIFEST.in
README.rst
apparmor-monkeys.pth
requirements.txt
setup.cfg
setup.py
apparmor_monkeys/__init__.py
apparmor_monkeys/ctypes.py
apparmor_monkeys/platform.py
apparmor_monkeys/tests.py
apparmor_monkeys.egg-info/PKG-INFO
apparmor_monkeys.egg-info/SOURCES.txt
apparmor_monkeys.egg-info/dependency_links.txt
apparmor_monkeys.egg-info/not-zip-safe
apparmor_monkeys.egg-info/top_level.txt